buckets/__init__.py
buckets/__main__.py
buckets/fake/__init__.py
buckets/fake/cases_rows.py
buckets/fake/console.py
buckets/fake/dates.py
buckets/fake/users.py
buckets/services/__init__.py
buckets/services/cases_buckets.py
buckets/services/config_service.py
buckets/services/graph_service.py
buckets/services/parser_service.py
buckets/services/schema_service.py
buckets-1.0.14.dist-info/entry_points.txt
buckets-1.0.14.dist-info/WHEEL
buckets-1.0.14.dist-info/METADATA
buckets-1.0.14.dist-info/RECORD
